docker_craft/__about__.py
docker_craft/__init__.py
docker_craft/__main__.py
docker_craft/cli/__init__.py
docker_craft-0.0.1.dist-info/METADATA
docker_craft-0.0.1.dist-info/WHEEL
docker_craft-0.0.1.dist-info/entry_points.txt
docker_craft-0.0.1.dist-info/licenses/LICENSE.txt
docker_craft-0.0.1.dist-info/RECORD
