Metadata-Version: 2.1
Name: docker-craft
Version: 0.0.1
Project-URL: Documentation, https://github.com/unknown/docker-craft#readme
Project-URL: Issues, https://github.com/unknown/docker-craft/issues
Project-URL: Source, https://github.com/unknown/docker-craft
Author-email: Julien Kieffer <julien@mefa.tech>
License-Expression: BSD-3-Clause
License-File: LICENSE.txt
Classifier: Development Status :: 4 - Beta
Classifier: Programming Language :: Python
Classifier: Programming Language :: Python :: 3.7
Classifier: Programming Language :: Python :: 3.8
Classifier: Programming Language :: Python :: 3.9
Classifier: Programming Language :: Python :: 3.10
Classifier: Programming Language :: Python :: 3.11
Classifier: Programming Language :: Python :: Implementation :: CPython
Classifier: Programming Language :: Python :: Implementation :: PyPy
Requires-Python: >=3.7
Requires-Dist: click
